{"stats":{"minecraft:mined":{"minecraft:tall_grass":8,"minecraft:cherry_log":2,"minecraft:pink_petals":2,"minecraft:short_grass":5},"minecraft:custom":{"minecraft:jump":69,"minecraft:time_since_rest":443,"minecraft:deaths":1,"minecraft:damage_dealt":89,"minecraft:damage_taken":275,"minecraft:leave_game":4,"minecraft:play_time":2806,"minecraft:sprint_one_cm":10985,"minecraft:time_since_death":415,"minecraft:walk_one_cm":4526,"minecraft:total_world_time":2806,"minecraft:fall_one_cm":2510,"minecraft:fly_one_cm":15491},"minecraft:picked_up":{"minecraft:cherry_log":2},"minecraft:used":{"minecraft:cherry_log":1},"minecraft:killed_by":{"minecraft:zombie":1}},"DataVersion":3953}